hivecrew/__init__.py
hivecrew/client.py
hivecrew/exceptions.py
hivecrew/models.py
hivecrew/py.typed
hivecrew/resources/__init__.py
hivecrew/resources/providers.py
hivecrew/resources/schedules.py
hivecrew/resources/system.py
hivecrew/resources/tasks.py
hivecrew/resources/templates.py
hivecrew-0.2.0.dist-info/METADATA
hivecrew-0.2.0.dist-info/WHEEL
hivecrew-0.2.0.dist-info/licenses/LICENSE
hivecrew-0.2.0.dist-info/RECORD
