Metadata-Version: 2.4
Name: hivecrew
Version: 0.2.0
Summary: Python SDK for the Hivecrew REST API
Project-URL: Homepage, https://github.com/hivecrew/hivecrew-python
Project-URL: Documentation, https://github.com/hivecrew/hivecrew-python#readme
Project-URL: Repository, https://github.com/hivecrew/hivecrew-python
Project-URL: Issues, https://github.com/hivecrew/hivecrew-python/issues
Author: Hivecrew
License-Expression: MIT
License-File: LICENSE
Keywords: agent,api,automation,computer-use,hivecrew,sdk
Classifier: Development Status :: 4 - Beta
Classifier: Intended Audience :: Developers
Classifier: License :: OSI Approved :: MIT License
Classifier: Operating System :: OS Independent
Classifier: Programming Language :: Python :: 3
Classifier: Programming Language :: Python :: 3.9
Classifier: Programming Language :: Python :: 3.10
Classifier: Programming Language :: Python :: 3.11
Classifier: Programming Language :: Python :: 3.12
Classifier: Programming Language :: Python :: 3.13
Classifier: Typing :: Typed
Requires-Python: >=3.9
Requires-Dist: pydantic>=2.0.0
Requires-Dist: requests>=2.28.0
Provides-Extra: dev
Requires-Dist: mypy>=1.0.0; extra == 'dev'
Requires-Dist: pytest-cov>=4.0.0; extra == 'dev'
Requires-Dist: pytest>=7.0.0; extra == 'dev'
Requires-Dist: ruff>=0.1.0; extra == 'dev'
Requires-Dist: types-requests>=2.28.0; extra == 'dev'
